{
  "stockCode": "601012",
  "stockName": "隆基绿能",
  "stockType": "trend",
  "bestConfig": {
    "minZoneCapture": 0.7,
    "zoneForward": 15,
    "zoneBackward": 2,
    "envFilter": "none"
  },
  "bestResult": {
    "stopLossRate": 0,
    "avgReturn": 0.0464,
    "totalTrades": 8,
    "winRate": 0.75,
    "maxDrawdown": -0.0191,
    "skippedByEnvironment": 0,
    "skippedByMarket": 67,
    "avgStopLossPct": 0.0511,
    "buyCount": 220,
    "trades": [
      {
        "buyDate": "2023-06-13",
        "sellDate": "2023-06-30",
        "buyPrice": 27.75,
        "sellPrice": 28.67,
        "return": 0.0319,
        "holdingDays": 11,
        "confidence": 0.6126,
        "stopLossPct": 0.0505,
        "exitReason": "timeout"
      },
      {
        "buyDate": "2024-04-15",
        "sellDate": "2024-04-24",
        "buyPrice": 18.69,
        "sellPrice": 18.5,
        "return": -0.0115,
        "holdingDays": 7,
        "confidence": 0.5986,
        "stopLossPct": 0.0385,
        "exitReason": "trailingStop"
      },
      {
        "buyDate": "2024-07-12",
        "sellDate": "2024-07-31",
        "buyPrice": 14.18,
        "sellPrice": 14.5,
        "return": 0.0213,
        "holdingDays": 13,
        "confidence": 0.6281,
        "stopLossPct": 0.0575,
        "exitReason": "sellSignal"
      },
      {
        "buyDate": "2025-04-25",
        "sellDate": "2025-05-15",
        "buyPrice": 14.89,
        "sellPrice": 15.09,
        "return": 0.0121,
        "holdingDays": 11,
        "confidence": 0.5237,
        "stopLossPct": 0.0378,
        "exitReason": "trailingStop"
      },
      {
        "buyDate": "2025-09-23",
        "sellDate": "2025-10-21",
        "buyPrice": 16.29,
        "sellPrice": 19.01,
        "return": 0.1657,
        "holdingDays": 14,
        "confidence": 0.5993,
        "stopLossPct": 0.0543,
        "exitReason": "trailingStop"
      },
      {
        "buyDate": "2025-10-27",
        "sellDate": "2025-11-05",
        "buyPrice": 19.06,
        "sellPrice": 21.85,
        "return": 0.1451,
        "holdingDays": 7,
        "confidence": 0.5178,
        "stopLossPct": 0.06,
        "exitReason": "sellSignal"
      },
      {
        "buyDate": "2025-11-13",
        "sellDate": "2025-11-14",
        "buyPrice": 21.3,
        "sellPrice": 21.88,
        "return": 0.0259,
        "holdingDays": 1,
        "confidence": 0.5069,
        "stopLossPct": 0.06,
        "exitReason": "sellSignal"
      },
      {
        "buyDate": "2025-12-05",
        "sellDate": "2025-12-18",
        "buyPrice": 18.02,
        "sellPrice": 17.7,
        "return": -0.0191,
        "holdingDays": 9,
        "confidence": 0.7419,
        "stopLossPct": 0.0501,
        "exitReason": "timeout"
      }
    ]
  },
  "bestModel": {
    "featureSet": "quality_momentum",
    "model": "EnsembleVote",
    "precision": 0.4889,
    "recall": 0.1005,
    "f1": 0.1549
  },
  "leaderboard": [
    {
      "rank": 1,
      "config": {
        "minZoneCapture": 0.7,
        "zoneForward": 15,
        "zoneBackward": 2,
        "envFilter": "none"
      },
      "bestModel": {
        "featureSet": "quality_momentum",
        "model": "EnsembleVote",
        "precision": 0.4889,
        "recall": 0.1005,
        "f1": 0.1549
      },
      "result": {
        "stopLossRate": 0,
        "avgReturn": 0.0464,
        "totalTrades": 8,
        "winRate": 0.75,
        "maxDrawdown": -0.0191,
        "skippedByEnvironment": 0,
        "skippedByMarket": 67,
        "avgStopLossPct": 0.0511,
        "buyCount": 220,
        "trades": [
          {
            "buyDate": "2023-06-13",
            "sellDate": "2023-06-30",
            "buyPrice": 27.75,
            "sellPrice": 28.67,
            "return": 0.0319,
            "holdingDays": 11,
            "confidence": 0.6126,
            "stopLossPct": 0.0505,
            "exitReason": "timeout"
          },
          {
            "buyDate": "2024-04-15",
            "sellDate": "2024-04-24",
            "buyPrice": 18.69,
            "sellPrice": 18.5,
            "return": -0.0115,
            "holdingDays": 7,
            "confidence": 0.5986,
            "stopLossPct": 0.0385,
            "exitReason": "trailingStop"
          },
          {
            "buyDate": "2024-07-12",
            "sellDate": "2024-07-31",
            "buyPrice": 14.18,
            "sellPrice": 14.5,
            "return": 0.0213,
            "holdingDays": 13,
            "confidence": 0.6281,
            "stopLossPct": 0.0575,
            "exitReason": "sellSignal"
          },
          {
            "buyDate": "2025-04-25",
            "sellDate": "2025-05-15",
            "buyPrice": 14.89,
            "sellPrice": 15.09,
            "return": 0.0121,
            "holdingDays": 11,
            "confidence": 0.5237,
            "stopLossPct": 0.0378,
            "exitReason": "trailingStop"
          },
          {
            "buyDate": "2025-09-23",
            "sellDate": "2025-10-21",
            "buyPrice": 16.29,
            "sellPrice": 19.01,
            "return": 0.1657,
            "holdingDays": 14,
            "confidence": 0.5993,
            "stopLossPct": 0.0543,
            "exitReason": "trailingStop"
          },
          {
            "buyDate": "2025-10-27",
            "sellDate": "2025-11-05",
            "buyPrice": 19.06,
            "sellPrice": 21.85,
            "return": 0.1451,
            "holdingDays": 7,
            "confidence": 0.5178,
            "stopLossPct": 0.06,
            "exitReason": "sellSignal"
          },
          {
            "buyDate": "2025-11-13",
            "sellDate": "2025-11-14",
            "buyPrice": 21.3,
            "sellPrice": 21.88,
            "return": 0.0259,
            "holdingDays": 1,
            "confidence": 0.5069,
            "stopLossPct": 0.06,
            "exitReason": "sellSignal"
          },
          {
            "buyDate": "2025-12-05",
            "sellDate": "2025-12-18",
            "buyPrice": 18.02,
            "sellPrice": 17.7,
            "return": -0.0191,
            "holdingDays": 9,
            "confidence": 0.7419,
            "stopLossPct": 0.0501,
            "exitReason": "timeout"
          }
        ]
      }
    },
    {
      "rank": 2,
      "config": {
        "minZoneCapture": 0.7,
        "zoneForward": 10,
        "zoneBackward": 5,
        "envFilter": "none"
      },
      "bestModel": {
        "featureSet": "quality_momentum",
        "model": "PercentileRank",
        "precision": 0.475,
        "recall": 0.0754,
        "f1": 0.1125
      },
      "result": {
        "stopLossRate": 0,
        "avgReturn": 0.0191,
        "totalTrades": 8,
        "winRate": 0.75,
        "maxDrawdown": -0.038,
        "skippedByEnvironment": 0,
        "skippedByMarket": 58,
        "avgStopLossPct": 0.0465,
        "buyCount": 216,
        "trades": [
          {
            "buyDate": "2022-11-14",
            "sellDate": "2022-12-02",
            "buyPrice": 47.35,
            "sellPrice": 47.98,
            "return": 0.012,
            "holdingDays": 14,
            "confidence": 0.5984,
            "stopLossPct": 0.06,
            "exitReason": "sellSignal"
          },
          {
            "buyDate": "2023-06-13",
            "sellDate": "2023-06-30",
            "buyPrice": 27.75,
            "sellPrice": 28.67,
            "return": 0.0319,
            "holdingDays": 11,
            "confidence": 0.9112,
            "stopLossPct": 0.0505,
            "exitReason": "timeout"
          },
          {
            "buyDate": "2024-04-15",
            "sellDate": "2024-04-24",
            "buyPrice": 18.69,
            "sellPrice": 18.5,
            "return": -0.0115,
            "holdingDays": 7,
            "confidence": 0.5189,
            "stopLossPct": 0.0385,
            "exitReason": "trailingStop"
          },
          {
            "buyDate": "2024-07-15",
            "sellDate": "2024-07-31",
            "buyPrice": 13.89,
            "sellPrice": 14.5,
            "return": 0.0426,
            "holdingDays": 12,
            "confidence": 0.5215,
            "stopLossPct": 0.0555,
            "exitReason": "sellSignal"
          },
          {
            "buyDate": "2025-07-01",
            "sellDate": "2025-07-07",
            "buyPrice": 14.86,
            "sellPrice": 15.47,
            "return": 0.0397,
            "holdingDays": 4,
            "confidence": 0.512,
            "stopLossPct": 0.0342,
            "exitReason": "sellSignal"
          },
          {
            "buyDate": "2025-07-09",
            "sellDate": "2025-07-10",
            "buyPrice": 16.37,
            "sellPrice": 16.46,
            "return": 0.0042,
            "holdingDays": 1,
            "confidence": 0.7395,
            "stopLossPct": 0.0423,
            "exitReason": "sellSignal"
          },
          {
            "buyDate": "2025-07-23",
            "sellDate": "2025-07-31",
            "buyPrice": 16.36,
            "sellPrice": 15.76,
            "return": -0.038,
            "holdingDays": 6,
            "confidence": 0.5481,
            "stopLossPct": 0.0402,
            "exitReason": "trailingStop"
          },
          {
            "buyDate": "2025-09-25",
            "sellDate": "2025-10-20",
            "buyPrice": 17.76,
            "sellPrice": 19.06,
            "return": 0.0719,
            "holdingDays": 11,
            "confidence": 0.5577,
            "stopLossPct": 0.0507,
            "exitReason": "trailingStop"
          }
        ]
      }
    },
    {
      "rank": 3,
      "config": {
        "minZoneCapture": 0.5,
        "zoneForward": 10,
        "zoneBackward": 5,
        "envFilter": "ma20"
      },
      "bestModel": {
        "featureSet": "quality_momentum",
        "model": "PercentileRank",
        "precision": 0.8,
        "recall": 0.0883,
        "f1": 0.1322
      },
      "result": {
        "stopLossRate": 0,
        "avgReturn": 0.0349,
        "totalTrades": 9,
        "winRate": 0.6667,
        "maxDrawdown": -0.0451,
        "skippedByEnvironment": 89,
        "skippedByMarket": 2,
        "avgStopLossPct": 0.0489,
        "buyCount": 308,
        "trades": [
          {
            "buyDate": "2023-07-11",
            "sellDate": "2023-07-12",
            "buyPrice": 29.24,
            "sellPrice": 30.55,
            "return": 0.0435,
            "holdingDays": 1,
            "confidence": 0.5205,
            "stopLossPct": 0.0492,
            "exitReason": "sellSignal"
          },
          {
            "buyDate": "2023-09-06",
            "sellDate": "2023-09-07",
            "buyPrice": 27.87,
            "sellPrice": 26.74,
            "return": -0.0418,
            "holdingDays": 1,
            "confidence": 0.5429,
            "stopLossPct": 0.0539,
            "exitReason": "sellSignal"
          },
          {
            "buyDate": "2024-10-16",
            "sellDate": "2024-10-23",
            "buyPrice": 15.93,
            "sellPrice": 19.58,
            "return": 0.2278,
            "holdingDays": 5,
            "confidence": 0.6243,
            "stopLossPct": 0.06,
            "exitReason": "sellSignal"
          },
          {
            "buyDate": "2025-07-01",
            "sellDate": "2025-07-07",
            "buyPrice": 14.86,
            "sellPrice": 15.47,
            "return": 0.0397,
            "holdingDays": 4,
            "confidence": 0.656,
            "stopLossPct": 0.0342,
            "exitReason": "sellSignal"
          },
          {
            "buyDate": "2025-07-09",
            "sellDate": "2025-07-10",
            "buyPrice": 16.37,
            "sellPrice": 16.46,
            "return": 0.0042,
            "holdingDays": 1,
            "confidence": 0.8835,
            "stopLossPct": 0.0423,
            "exitReason": "sellSignal"
          },
          {
            "buyDate": "2025-07-23",
            "sellDate": "2025-07-31",
            "buyPrice": 16.36,
            "sellPrice": 15.76,
            "return": -0.038,
            "holdingDays": 6,
            "confidence": 0.6922,
            "stopLossPct": 0.0402,
            "exitReason": "trailingStop"
          },
          {
            "buyDate": "2025-09-05",
            "sellDate": "2025-09-08",
            "buyPrice": 18.1,
            "sellPrice": 17.99,
            "return": -0.0074,
            "holdingDays": 1,
            "confidence": 0.5122,
            "stopLossPct": 0.0497,
            "exitReason": "sellSignal"
          },
          {
            "buyDate": "2025-09-25",
            "sellDate": "2025-10-20",
            "buyPrice": 17.76,
            "sellPrice": 19.06,
            "return": 0.0719,
            "holdingDays": 11,
            "confidence": 0.5759,
            "stopLossPct": 0.0507,
            "exitReason": "trailingStop"
          },
          {
            "buyDate": "2025-10-30",
            "sellDate": "2025-11-05",
            "buyPrice": 21.51,
            "sellPrice": 21.85,
            "return": 0.0145,
            "holdingDays": 4,
            "confidence": 0.8503,
            "stopLossPct": 0.06,
            "exitReason": "sellSignal"
          }
        ]
      }
    },
    {
      "rank": 4,
      "config": {
        "minZoneCapture": 0.6,
        "zoneForward": 3,
        "zoneBackward": 5,
        "envFilter": "ma60_rising"
      },
      "bestModel": {
        "featureSet": "breakout_ready",
        "model": "PositiveBiasRank",
        "precision": 0.3314,
        "recall": 0.1834,
        "f1": 0.1538
      },
      "result": {
        "stopLossRate": 0,
        "avgReturn": 0.0444,
        "totalTrades": 11,
        "winRate": 0.5455,
        "maxDrawdown": -0.0388,
        "skippedByEnvironment": 129,
        "skippedByMarket": 5,
        "avgStopLossPct": 0.0522,
        "buyCount": 181,
        "trades": [
          {
            "buyDate": "2024-03-12",
            "sellDate": "2024-03-13",
            "buyPrice": 22.32,
            "sellPrice": 21.89,
            "return": -0.0206,
            "holdingDays": 1,
            "confidence": 0.5921,
            "stopLossPct": 0.0481,
            "exitReason": "sellSignal"
          },
          {
            "buyDate": "2024-10-11",
            "sellDate": "2024-10-23",
            "buyPrice": 16.2,
            "sellPrice": 19.58,
            "return": 0.2073,
            "holdingDays": 8,
            "confidence": 0.7525,
            "stopLossPct": 0.06,
            "exitReason": "sellSignal"
          },
          {
            "buyDate": "2024-10-25",
            "sellDate": "2024-10-28",
            "buyPrice": 20.46,
            "sellPrice": 20.08,
            "return": -0.0199,
            "holdingDays": 1,
            "confidence": 0.6515,
            "stopLossPct": 0.06,
            "exitReason": "sellSignal"
          },
          {
            "buyDate": "2025-03-20",
            "sellDate": "2025-03-26",
            "buyPrice": 17.43,
            "sellPrice": 17.36,
            "return": -0.0053,
            "holdingDays": 4,
            "confidence": 0.6101,
            "stopLossPct": 0.043,
            "exitReason": "timeout"
          },
          {
            "buyDate": "2025-07-10",
            "sellDate": "2025-07-11",
            "buyPrice": 16.46,
            "sellPrice": 16.25,
            "return": -0.0141,
            "holdingDays": 1,
            "confidence": 0.5,
            "stopLossPct": 0.0416,
            "exitReason": "sellSignal"
          },
          {
            "buyDate": "2025-08-04",
            "sellDate": "2025-09-03",
            "buyPrice": 15.78,
            "sellPrice": 17.18,
            "return": 0.0874,
            "holdingDays": 22,
            "confidence": 0.5,
            "stopLossPct": 0.0399,
            "exitReason": "sellSignal"
          },
          {
            "buyDate": "2025-09-08",
            "sellDate": "2025-09-09",
            "buyPrice": 17.99,
            "sellPrice": 17.61,
            "return": -0.0224,
            "holdingDays": 1,
            "confidence": 0.5,
            "stopLossPct": 0.0506,
            "exitReason": "sellSignal"
          },
          {
            "buyDate": "2025-09-25",
            "sellDate": "2025-10-20",
            "buyPrice": 17.76,
            "sellPrice": 19.06,
            "return": 0.0719,
            "holdingDays": 11,
            "confidence": 0.5,
            "stopLossPct": 0.0507,
            "exitReason": "trailingStop"
          },
          {
            "buyDate": "2025-10-22",
            "sellDate": "2025-11-05",
            "buyPrice": 18.77,
            "sellPrice": 21.85,
            "return": 0.1628,
            "holdingDays": 10,
            "confidence": 0.5,
            "stopLossPct": 0.06,
            "exitReason": "sellSignal"
          },
          {
            "buyDate": "2025-11-07",
            "sellDate": "2025-11-10",
            "buyPrice": 22.43,
            "sellPrice": 22.8,
            "return": 0.0152,
            "holdingDays": 1,
            "confidence": 0.5,
            "stopLossPct": 0.06,
            "exitReason": "sellSignal"
          },
          {
            "buyDate": "2025-11-13",
            "sellDate": "2025-11-14",
            "buyPrice": 21.3,
            "sellPrice": 21.88,
            "return": 0.0259,
            "holdingDays": 1,
            "confidence": 0.5,
            "stopLossPct": 0.06,
            "exitReason": "sellSignal"
          }
        ]
      }
    },
    {
      "rank": 5,
      "config": {
        "minZoneCapture": 0.5,
        "zoneForward": 10,
        "zoneBackward": 5,
        "envFilter": "ma20_0.98"
      },
      "bestModel": {
        "featureSet": "quality_momentum",
        "model": "PercentileRank",
        "precision": 0.8,
        "recall": 0.0883,
        "f1": 0.1322
      },
      "result": {
        "stopLossRate": 0.0909,
        "avgReturn": 0.0259,
        "totalTrades": 11,
        "winRate": 0.6364,
        "maxDrawdown": -0.0451,
        "skippedByEnvironment": 81,
        "skippedByMarket": 3,
        "avgStopLossPct": 0.0463,
        "buyCount": 308,
        "trades": [
          {
            "buyDate": "2023-04-14",
            "sellDate": "2023-04-20",
            "buyPrice": 39.26,
            "sellPrice": 37.61,
            "return": -0.0433,
            "holdingDays": 4,
            "confidence": 0.5172,
            "stopLossPct": 0.0341,
            "exitReason": "stopLoss"
          },
          {
            "buyDate": "2023-07-11",
            "sellDate": "2023-07-12",
            "buyPrice": 29.24,
            "sellPrice": 30.55,
            "return": 0.0435,
            "holdingDays": 1,
            "confidence": 0.5205,
            "stopLossPct": 0.0492,
            "exitReason": "sellSignal"
          },
          {
            "buyDate": "2023-09-06",
            "sellDate": "2023-09-07",
            "buyPrice": 27.87,
            "sellPrice": 26.74,
            "return": -0.0418,
            "holdingDays": 1,
            "confidence": 0.5429,
            "stopLossPct": 0.0539,
            "exitReason": "sellSignal"
          },
          {
            "buyDate": "2024-10-16",
            "sellDate": "2024-10-23",
            "buyPrice": 15.93,
            "sellPrice": 19.58,
            "return": 0.2278,
            "holdingDays": 5,
            "confidence": 0.6243,
            "stopLossPct": 0.06,
            "exitReason": "sellSignal"
          },
          {
            "buyDate": "2025-04-29",
            "sellDate": "2025-05-15",
            "buyPrice": 14.86,
            "sellPrice": 15.09,
            "return": 0.0142,
            "holdingDays": 9,
            "confidence": 0.5184,
            "stopLossPct": 0.0345,
            "exitReason": "trailingStop"
          },
          {
            "buyDate": "2025-07-01",
            "sellDate": "2025-07-07",
            "buyPrice": 14.86,
            "sellPrice": 15.47,
            "return": 0.0397,
            "holdingDays": 4,
            "confidence": 0.656,
            "stopLossPct": 0.0342,
            "exitReason": "sellSignal"
          },
          {
            "buyDate": "2025-07-09",
            "sellDate": "2025-07-10",
            "buyPrice": 16.37,
            "sellPrice": 16.46,
            "return": 0.0042,
            "holdingDays": 1,
            "confidence": 0.8835,
            "stopLossPct": 0.0423,
            "exitReason": "sellSignal"
          },
          {
            "buyDate": "2025-07-23",
            "sellDate": "2025-07-31",
            "buyPrice": 16.36,
            "sellPrice": 15.76,
            "return": -0.038,
            "holdingDays": 6,
            "confidence": 0.6922,
            "stopLossPct": 0.0402,
            "exitReason": "trailingStop"
          },
          {
            "buyDate": "2025-09-05",
            "sellDate": "2025-09-08",
            "buyPrice": 18.1,
            "sellPrice": 17.99,
            "return": -0.0074,
            "holdingDays": 1,
            "confidence": 0.5122,
            "stopLossPct": 0.0497,
            "exitReason": "sellSignal"
          },
          {
            "buyDate": "2025-09-25",
            "sellDate": "2025-10-20",
            "buyPrice": 17.76,
            "sellPrice": 19.06,
            "return": 0.0719,
            "holdingDays": 11,
            "confidence": 0.5759,
            "stopLossPct": 0.0507,
            "exitReason": "trailingStop"
          },
          {
            "buyDate": "2025-10-30",
            "sellDate": "2025-11-05",
            "buyPrice": 21.51,
            "sellPrice": 21.85,
            "return": 0.0145,
            "holdingDays": 4,
            "confidence": 0.8503,
            "stopLossPct": 0.06,
            "exitReason": "sellSignal"
          }
        ]
      }
    },
    {
      "rank": 6,
      "config": {
        "minZoneCapture": 0.5,
        "zoneForward": 10,
        "zoneBackward": 5,
        "envFilter": "ma20_or_ma60_rising"
      },
      "bestModel": {
        "featureSet": "quality_momentum",
        "model": "PercentileRank",
        "precision": 0.8,
        "recall": 0.0883,
        "f1": 0.1322
      },
      "result": {
        "stopLossRate": 0.0909,
        "avgReturn": 0.0259,
        "totalTrades": 11,
        "winRate": 0.6364,
        "maxDrawdown": -0.0451,
        "skippedByEnvironment": 81,
        "skippedByMarket": 3,
        "avgStopLossPct": 0.0463,
        "buyCount": 308,
        "trades": [
          {
            "buyDate": "2023-04-14",
            "sellDate": "2023-04-20",
            "buyPrice": 39.26,
            "sellPrice": 37.61,
            "return": -0.0433,
            "holdingDays": 4,
            "confidence": 0.5172,
            "stopLossPct": 0.0341,
            "exitReason": "stopLoss"
          },
          {
            "buyDate": "2023-07-11",
            "sellDate": "2023-07-12",
            "buyPrice": 29.24,
            "sellPrice": 30.55,
            "return": 0.0435,
            "holdingDays": 1,
            "confidence": 0.5205,
            "stopLossPct": 0.0492,
            "exitReason": "sellSignal"
          },
          {
            "buyDate": "2023-09-06",
            "sellDate": "2023-09-07",
            "buyPrice": 27.87,
            "sellPrice": 26.74,
            "return": -0.0418,
            "holdingDays": 1,
            "confidence": 0.5429,
            "stopLossPct": 0.0539,
            "exitReason": "sellSignal"
          },
          {
            "buyDate": "2024-10-16",
            "sellDate": "2024-10-23",
            "buyPrice": 15.93,
            "sellPrice": 19.58,
            "return": 0.2278,
            "holdingDays": 5,
            "confidence": 0.6243,
            "stopLossPct": 0.06,
            "exitReason": "sellSignal"
          },
          {
            "buyDate": "2025-04-29",
            "sellDate": "2025-05-15",
            "buyPrice": 14.86,
            "sellPrice": 15.09,
            "return": 0.0142,
            "holdingDays": 9,
            "confidence": 0.5184,
            "stopLossPct": 0.0345,
            "exitReason": "trailingStop"
          },
          {
            "buyDate": "2025-07-01",
            "sellDate": "2025-07-07",
            "buyPrice": 14.86,
            "sellPrice": 15.47,
            "return": 0.0397,
            "holdingDays": 4,
            "confidence": 0.656,
            "stopLossPct": 0.0342,
            "exitReason": "sellSignal"
          },
          {
            "buyDate": "2025-07-09",
            "sellDate": "2025-07-10",
            "buyPrice": 16.37,
            "sellPrice": 16.46,
            "return": 0.0042,
            "holdingDays": 1,
            "confidence": 0.8835,
            "stopLossPct": 0.0423,
            "exitReason": "sellSignal"
          },
          {
            "buyDate": "2025-07-23",
            "sellDate": "2025-07-31",
            "buyPrice": 16.36,
            "sellPrice": 15.76,
            "return": -0.038,
            "holdingDays": 6,
            "confidence": 0.6922,
            "stopLossPct": 0.0402,
            "exitReason": "trailingStop"
          },
          {
            "buyDate": "2025-09-05",
            "sellDate": "2025-09-08",
            "buyPrice": 18.1,
            "sellPrice": 17.99,
            "return": -0.0074,
            "holdingDays": 1,
            "confidence": 0.5122,
            "stopLossPct": 0.0497,
            "exitReason": "sellSignal"
          },
          {
            "buyDate": "2025-09-25",
            "sellDate": "2025-10-20",
            "buyPrice": 17.76,
            "sellPrice": 19.06,
            "return": 0.0719,
            "holdingDays": 11,
            "confidence": 0.5759,
            "stopLossPct": 0.0507,
            "exitReason": "trailingStop"
          },
          {
            "buyDate": "2025-10-30",
            "sellDate": "2025-11-05",
            "buyPrice": 21.51,
            "sellPrice": 21.85,
            "return": 0.0145,
            "holdingDays": 4,
            "confidence": 0.8503,
            "stopLossPct": 0.06,
            "exitReason": "sellSignal"
          }
        ]
      }
    },
    {
      "rank": 7,
      "config": {
        "minZoneCapture": 0.5,
        "zoneForward": 10,
        "zoneBackward": 5,
        "envFilter": "none"
      },
      "bestModel": {
        "featureSet": "quality_momentum",
        "model": "PercentileRank",
        "precision": 0.8,
        "recall": 0.0883,
        "f1": 0.1322
      },
      "result": {
        "stopLossRate": 0.0625,
        "avgReturn": 0.0235,
        "totalTrades": 16,
        "winRate": 0.625,
        "maxDrawdown": -0.0451,
        "skippedByEnvironment": 0,
        "skippedByMarket": 73,
        "avgStopLossPct": 0.0471,
        "buyCount": 308,
        "trades": [
          {
            "buyDate": "2023-04-14",
            "sellDate": "2023-04-20",
            "buyPrice": 39.26,
            "sellPrice": 37.61,
            "return": -0.0433,
            "holdingDays": 4,
            "confidence": 0.5172,
            "stopLossPct": 0.0341,
            "exitReason": "stopLoss"
          },
          {
            "buyDate": "2023-07-11",
            "sellDate": "2023-07-12",
            "buyPrice": 29.24,
            "sellPrice": 30.55,
            "return": 0.0435,
            "holdingDays": 1,
            "confidence": 0.5205,
            "stopLossPct": 0.0492,
            "exitReason": "sellSignal"
          },
          {
            "buyDate": "2023-09-06",
            "sellDate": "2023-09-07",
            "buyPrice": 27.87,
            "sellPrice": 26.74,
            "return": -0.0418,
            "holdingDays": 1,
            "confidence": 0.5429,
            "stopLossPct": 0.0539,
            "exitReason": "sellSignal"
          },
          {
            "buyDate": "2023-11-06",
            "sellDate": "2023-11-15",
            "buyPrice": 23.45,
            "sellPrice": 24.39,
            "return": 0.0388,
            "holdingDays": 7,
            "confidence": 0.6537,
            "stopLossPct": 0.055,
            "exitReason": "sellSignal"
          },
          {
            "buyDate": "2024-02-06",
            "sellDate": "2024-03-07",
            "buyPrice": 19.6,
            "sellPrice": 20.8,
            "return": 0.0599,
            "holdingDays": 16,
            "confidence": 0.5086,
            "stopLossPct": 0.06,
            "exitReason": "sellSignal"
          },
          {
            "buyDate": "2024-04-15",
            "sellDate": "2024-04-24",
            "buyPrice": 18.69,
            "sellPrice": 18.5,
            "return": -0.0115,
            "holdingDays": 7,
            "confidence": 0.6009,
            "stopLossPct": 0.0385,
            "exitReason": "trailingStop"
          },
          {
            "buyDate": "2024-07-12",
            "sellDate": "2024-07-31",
            "buyPrice": 14.18,
            "sellPrice": 14.5,
            "return": 0.0213,
            "holdingDays": 13,
            "confidence": 0.7256,
            "stopLossPct": 0.0575,
            "exitReason": "sellSignal"
          },
          {
            "buyDate": "2024-10-16",
            "sellDate": "2024-10-23",
            "buyPrice": 15.93,
            "sellPrice": 19.58,
            "return": 0.2278,
            "holdingDays": 5,
            "confidence": 0.6243,
            "stopLossPct": 0.06,
            "exitReason": "sellSignal"
          },
          {
            "buyDate": "2025-04-29",
            "sellDate": "2025-05-15",
            "buyPrice": 14.86,
            "sellPrice": 15.09,
            "return": 0.0142,
            "holdingDays": 9,
            "confidence": 0.5184,
            "stopLossPct": 0.0345,
            "exitReason": "trailingStop"
          },
          {
            "buyDate": "2025-07-01",
            "sellDate": "2025-07-07",
            "buyPrice": 14.86,
            "sellPrice": 15.47,
            "return": 0.0397,
            "holdingDays": 4,
            "confidence": 0.656,
            "stopLossPct": 0.0342,
            "exitReason": "sellSignal"
          },
          {
            "buyDate": "2025-07-09",
            "sellDate": "2025-07-10",
            "buyPrice": 16.37,
            "sellPrice": 16.46,
            "return": 0.0042,
            "holdingDays": 1,
            "confidence": 0.8835,
            "stopLossPct": 0.0423,
            "exitReason": "sellSignal"
          },
          {
            "buyDate": "2025-07-23",
            "sellDate": "2025-07-31",
            "buyPrice": 16.36,
            "sellPrice": 15.76,
            "return": -0.038,
            "holdingDays": 6,
            "confidence": 0.6922,
            "stopLossPct": 0.0402,
            "exitReason": "trailingStop"
          },
          {
            "buyDate": "2025-09-05",
            "sellDate": "2025-09-08",
            "buyPrice": 18.1,
            "sellPrice": 17.99,
            "return": -0.0074,
            "holdingDays": 1,
            "confidence": 0.5122,
            "stopLossPct": 0.0497,
            "exitReason": "sellSignal"
          },
          {
            "buyDate": "2025-09-25",
            "sellDate": "2025-10-20",
            "buyPrice": 17.76,
            "sellPrice": 19.06,
            "return": 0.0719,
            "holdingDays": 11,
            "confidence": 0.5759,
            "stopLossPct": 0.0507,
            "exitReason": "trailingStop"
          },
          {
            "buyDate": "2025-10-30",
            "sellDate": "2025-11-05",
            "buyPrice": 21.51,
            "sellPrice": 21.85,
            "return": 0.0145,
            "holdingDays": 4,
            "confidence": 0.8503,
            "stopLossPct": 0.06,
            "exitReason": "sellSignal"
          },
          {
            "buyDate": "2025-12-15",
            "sellDate": "2025-12-18",
            "buyPrice": 18,
            "sellPrice": 17.7,
            "return": -0.018,
            "holdingDays": 3,
            "confidence": 0.5032,
            "stopLossPct": 0.0339,
            "exitReason": "timeout"
          }
        ]
      }
    },
    {
      "rank": 8,
      "config": {
        "minZoneCapture": 0.6,
        "zoneForward": 10,
        "zoneBackward": 2,
        "envFilter": "ma20_0.98"
      },
      "bestModel": {
        "featureSet": "quality_momentum",
        "model": "PercentileRank",
        "precision": 0.7607,
        "recall": 0.0996,
        "f1": 0.1423
      },
      "result": {
        "stopLossRate": 0.125,
        "avgReturn": 0.0208,
        "totalTrades": 8,
        "winRate": 0.625,
        "maxDrawdown": -0.0414,
        "skippedByEnvironment": 104,
        "skippedByMarket": 5,
        "avgStopLossPct": 0.0444,
        "buyCount": 229,
        "trades": [
          {
            "buyDate": "2022-12-01",
            "sellDate": "2022-12-02",
            "buyPrice": 47.01,
            "sellPrice": 47.98,
            "return": 0.0193,
            "holdingDays": 1,
            "confidence": 0.5129,
            "stopLossPct": 0.0428,
            "exitReason": "sellSignal"
          },
          {
            "buyDate": "2023-06-15",
            "sellDate": "2023-06-30",
            "buyPrice": 29.18,
            "sellPrice": 28.67,
            "return": -0.0188,
            "holdingDays": 9,
            "confidence": 0.8665,
            "stopLossPct": 0.0482,
            "exitReason": "timeout"
          },
          {
            "buyDate": "2025-04-25",
            "sellDate": "2025-05-15",
            "buyPrice": 14.89,
            "sellPrice": 15.09,
            "return": 0.0121,
            "holdingDays": 11,
            "confidence": 0.5551,
            "stopLossPct": 0.0378,
            "exitReason": "trailingStop"
          },
          {
            "buyDate": "2025-06-12",
            "sellDate": "2025-06-19",
            "buyPrice": 14.74,
            "sellPrice": 14.33,
            "return": -0.0291,
            "holdingDays": 5,
            "confidence": 0.6003,
            "stopLossPct": 0.0282,
            "exitReason": "stopLoss"
          },
          {
            "buyDate": "2025-07-03",
            "sellDate": "2025-07-07",
            "buyPrice": 15.54,
            "sellPrice": 15.47,
            "return": -0.0058,
            "holdingDays": 2,
            "confidence": 0.5539,
            "stopLossPct": 0.0363,
            "exitReason": "sellSignal"
          },
          {
            "buyDate": "2025-07-09",
            "sellDate": "2025-07-10",
            "buyPrice": 16.37,
            "sellPrice": 16.46,
            "return": 0.0042,
            "holdingDays": 1,
            "confidence": 0.6106,
            "stopLossPct": 0.0423,
            "exitReason": "sellSignal"
          },
          {
            "buyDate": "2025-10-24",
            "sellDate": "2025-11-05",
            "buyPrice": 18.84,
            "sellPrice": 21.85,
            "return": 0.1585,
            "holdingDays": 8,
            "confidence": 0.5592,
            "stopLossPct": 0.06,
            "exitReason": "sellSignal"
          },
          {
            "buyDate": "2025-11-13",
            "sellDate": "2025-11-14",
            "buyPrice": 21.3,
            "sellPrice": 21.88,
            "return": 0.0259,
            "holdingDays": 1,
            "confidence": 0.6699,
            "stopLossPct": 0.06,
            "exitReason": "sellSignal"
          }
        ]
      }
    },
    {
      "rank": 9,
      "config": {
        "minZoneCapture": 0.6,
        "zoneForward": 10,
        "zoneBackward": 2,
        "envFilter": "ma20_or_ma60_rising"
      },
      "bestModel": {
        "featureSet": "quality_momentum",
        "model": "PercentileRank",
        "precision": 0.7607,
        "recall": 0.0996,
        "f1": 0.1423
      },
      "result": {
        "stopLossRate": 0.125,
        "avgReturn": 0.0208,
        "totalTrades": 8,
        "winRate": 0.625,
        "maxDrawdown": -0.0414,
        "skippedByEnvironment": 103,
        "skippedByMarket": 6,
        "avgStopLossPct": 0.0444,
        "buyCount": 229,
        "trades": [
          {
            "buyDate": "2022-12-01",
            "sellDate": "2022-12-02",
            "buyPrice": 47.01,
            "sellPrice": 47.98,
            "return": 0.0193,
            "holdingDays": 1,
            "confidence": 0.5129,
            "stopLossPct": 0.0428,
            "exitReason": "sellSignal"
          },
          {
            "buyDate": "2023-06-15",
            "sellDate": "2023-06-30",
            "buyPrice": 29.18,
            "sellPrice": 28.67,
            "return": -0.0188,
            "holdingDays": 9,
            "confidence": 0.8665,
            "stopLossPct": 0.0482,
            "exitReason": "timeout"
          },
          {
            "buyDate": "2025-04-25",
            "sellDate": "2025-05-15",
            "buyPrice": 14.89,
            "sellPrice": 15.09,
            "return": 0.0121,
            "holdingDays": 11,
            "confidence": 0.5551,
            "stopLossPct": 0.0378,
            "exitReason": "trailingStop"
          },
          {
            "buyDate": "2025-06-12",
            "sellDate": "2025-06-19",
            "buyPrice": 14.74,
            "sellPrice": 14.33,
            "return": -0.0291,
            "holdingDays": 5,
            "confidence": 0.6003,
            "stopLossPct": 0.0282,
            "exitReason": "stopLoss"
          },
          {
            "buyDate": "2025-07-03",
            "sellDate": "2025-07-07",
            "buyPrice": 15.54,
            "sellPrice": 15.47,
            "return": -0.0058,
            "holdingDays": 2,
            "confidence": 0.5539,
            "stopLossPct": 0.0363,
            "exitReason": "sellSignal"
          },
          {
            "buyDate": "2025-07-09",
            "sellDate": "2025-07-10",
            "buyPrice": 16.37,
            "sellPrice": 16.46,
            "return": 0.0042,
            "holdingDays": 1,
            "confidence": 0.6106,
            "stopLossPct": 0.0423,
            "exitReason": "sellSignal"
          },
          {
            "buyDate": "2025-10-24",
            "sellDate": "2025-11-05",
            "buyPrice": 18.84,
            "sellPrice": 21.85,
            "return": 0.1585,
            "holdingDays": 8,
            "confidence": 0.5592,
            "stopLossPct": 0.06,
            "exitReason": "sellSignal"
          },
          {
            "buyDate": "2025-11-13",
            "sellDate": "2025-11-14",
            "buyPrice": 21.3,
            "sellPrice": 21.88,
            "return": 0.0259,
            "holdingDays": 1,
            "confidence": 0.6699,
            "stopLossPct": 0.06,
            "exitReason": "sellSignal"
          }
        ]
      }
    },
    {
      "rank": 10,
      "config": {
        "minZoneCapture": 0.5,
        "zoneForward": 15,
        "zoneBackward": 5,
        "envFilter": "ma20"
      },
      "bestModel": {
        "featureSet": "quality_momentum",
        "model": "PercentileRank",
        "precision": 0.6778,
        "recall": 0.1102,
        "f1": 0.1655
      },
      "result": {
        "stopLossRate": 0.125,
        "avgReturn": 0.0468,
        "totalTrades": 8,
        "winRate": 0.5,
        "maxDrawdown": -0.0503,
        "skippedByEnvironment": 141,
        "skippedByMarket": 3,
        "avgStopLossPct": 0.0469,
        "buyCount": 357,
        "trades": [
          {
            "buyDate": "2023-09-06",
            "sellDate": "2023-09-07",
            "buyPrice": 27.87,
            "sellPrice": 26.74,
            "return": -0.0418,
            "holdingDays": 1,
            "confidence": 0.5124,
            "stopLossPct": 0.0539,
            "exitReason": "sellSignal"
          },
          {
            "buyDate": "2024-10-16",
            "sellDate": "2024-10-23",
            "buyPrice": 15.93,
            "sellPrice": 19.58,
            "return": 0.2278,
            "holdingDays": 5,
            "confidence": 0.6243,
            "stopLossPct": 0.06,
            "exitReason": "sellSignal"
          },
          {
            "buyDate": "2025-03-17",
            "sellDate": "2025-03-26",
            "buyPrice": 17.67,
            "sellPrice": 17.36,
            "return": -0.0188,
            "holdingDays": 7,
            "confidence": 0.5069,
            "stopLossPct": 0.0508,
            "exitReason": "timeout"
          },
          {
            "buyDate": "2025-05-06",
            "sellDate": "2025-05-15",
            "buyPrice": 15.03,
            "sellPrice": 15.09,
            "return": 0.0027,
            "holdingDays": 7,
            "confidence": 0.5346,
            "stopLossPct": 0.0338,
            "exitReason": "trailingStop"
          },
          {
            "buyDate": "2025-06-12",
            "sellDate": "2025-06-19",
            "buyPrice": 14.74,
            "sellPrice": 14.33,
            "return": -0.0291,
            "holdingDays": 5,
            "confidence": 0.5925,
            "stopLossPct": 0.0282,
            "exitReason": "stopLoss"
          },
          {
            "buyDate": "2025-07-03",
            "sellDate": "2025-07-07",
            "buyPrice": 15.54,
            "sellPrice": 15.47,
            "return": -0.0058,
            "holdingDays": 2,
            "confidence": 0.5404,
            "stopLossPct": 0.0363,
            "exitReason": "sellSignal"
          },
          {
            "buyDate": "2025-09-24",
            "sellDate": "2025-10-20",
            "buyPrice": 17.4,
            "sellPrice": 19.06,
            "return": 0.0941,
            "holdingDays": 12,
            "confidence": 0.7561,
            "stopLossPct": 0.0522,
            "exitReason": "trailingStop"
          },
          {
            "buyDate": "2025-10-27",
            "sellDate": "2025-11-05",
            "buyPrice": 19.06,
            "sellPrice": 21.85,
            "return": 0.1451,
            "holdingDays": 7,
            "confidence": 0.509,
            "stopLossPct": 0.06,
            "exitReason": "sellSignal"
          }
        ]
      }
    }
  ],
  "stats": {
    "totalCombinations": 240,
    "validCombinations": 50,
    "scanDurationMs": 171847
  },
  "currentSignal": {
    "signal": "hold",
    "confidence": 0.602,
    "score": 0.39,
    "threshold": 0.647,
    "reason": "模型打分 0.390 未超过阈值 0.647；当前大盘在 MA20 下方，信号仅供参考",
    "date": "2026-03-20",
    "close": 18.99,
    "isBuyZone": false,
    "isSellZone": false
  }
}