{
  "stockCode": "603156",
  "stockName": "养元饮品",
  "stockType": "trend",
  "bestConfig": {
    "minZoneCapture": 0.6,
    "zoneForward": 15,
    "zoneBackward": 2,
    "envFilter": "ma20_or_ma60_rising"
  },
  "bestResult": {
    "stopLossRate": 0.1818,
    "avgReturn": 0.0454,
    "totalTrades": 11,
    "winRate": 0.8182,
    "maxDrawdown": -0.0462,
    "skippedByEnvironment": 30,
    "skippedByMarket": 12,
    "avgStopLossPct": 0.0413,
    "buyCount": 252,
    "trades": [
      {
        "buyDate": "2022-11-30",
        "sellDate": "2022-12-07",
        "buyPrice": 20,
        "sellPrice": 21.54,
        "return": 0.0757,
        "holdingDays": 5,
        "confidence": 0.6977,
        "stopLossPct": 0.0266,
        "exitReason": "sellSignal"
      },
      {
        "buyDate": "2022-12-09",
        "sellDate": "2022-12-12",
        "buyPrice": 21.65,
        "sellPrice": 22.16,
        "return": 0.0223,
        "holdingDays": 1,
        "confidence": 1,
        "stopLossPct": 0.0417,
        "exitReason": "sellSignal"
      },
      {
        "buyDate": "2024-03-08",
        "sellDate": "2024-03-15",
        "buyPrice": 24.49,
        "sellPrice": 25.79,
        "return": 0.0518,
        "holdingDays": 5,
        "confidence": 0.5378,
        "stopLossPct": 0.0434,
        "exitReason": "sellSignal"
      },
      {
        "buyDate": "2024-07-15",
        "sellDate": "2024-07-23",
        "buyPrice": 21.39,
        "sellPrice": 20.57,
        "return": -0.0396,
        "holdingDays": 6,
        "confidence": 0.612,
        "stopLossPct": 0.0344,
        "exitReason": "stopLoss"
      },
      {
        "buyDate": "2024-09-25",
        "sellDate": "2024-09-26",
        "buyPrice": 19.57,
        "sellPrice": 20.53,
        "return": 0.0478,
        "holdingDays": 1,
        "confidence": 1,
        "stopLossPct": 0.0415,
        "exitReason": "sellSignal"
      },
      {
        "buyDate": "2024-09-30",
        "sellDate": "2024-10-08",
        "buyPrice": 23.14,
        "sellPrice": 23.44,
        "return": 0.0117,
        "holdingDays": 1,
        "confidence": 0.9216,
        "stopLossPct": 0.0491,
        "exitReason": "sellSignal"
      },
      {
        "buyDate": "2024-10-29",
        "sellDate": "2024-12-11",
        "buyPrice": 20.91,
        "sellPrice": 22.35,
        "return": 0.0676,
        "holdingDays": 31,
        "confidence": 0.5252,
        "stopLossPct": 0.0518,
        "exitReason": "sellSignal"
      },
      {
        "buyDate": "2025-04-29",
        "sellDate": "2025-05-06",
        "buyPrice": 24.97,
        "sellPrice": 23.85,
        "return": -0.0462,
        "holdingDays": 2,
        "confidence": 0.8104,
        "stopLossPct": 0.043,
        "exitReason": "stopLoss"
      },
      {
        "buyDate": "2025-07-08",
        "sellDate": "2025-09-02",
        "buyPrice": 21.12,
        "sellPrice": 21.7,
        "return": 0.0262,
        "holdingDays": 40,
        "confidence": 1,
        "stopLossPct": 0.0214,
        "exitReason": "timeout"
      },
      {
        "buyDate": "2025-09-25",
        "sellDate": "2025-09-29",
        "buyPrice": 25.58,
        "sellPrice": 30.3,
        "return": 0.1832,
        "holdingDays": 2,
        "confidence": 1,
        "stopLossPct": 0.041,
        "exitReason": "sellSignal"
      },
      {
        "buyDate": "2025-10-09",
        "sellDate": "2025-10-10",
        "buyPrice": 31.29,
        "sellPrice": 34.42,
        "return": 0.0987,
        "holdingDays": 1,
        "confidence": 1,
        "stopLossPct": 0.06,
        "exitReason": "sellSignal"
      }
    ]
  },
  "bestModel": {
    "featureSet": "volume_price",
    "model": "PercentileRank",
    "precision": 0.3078,
    "recall": 0.7094,
    "f1": 0.4045
  },
  "leaderboard": [
    {
      "rank": 1,
      "config": {
        "minZoneCapture": 0.6,
        "zoneForward": 15,
        "zoneBackward": 2,
        "envFilter": "ma20_or_ma60_rising"
      },
      "bestModel": {
        "featureSet": "volume_price",
        "model": "PercentileRank",
        "precision": 0.3078,
        "recall": 0.7094,
        "f1": 0.4045
      },
      "result": {
        "stopLossRate": 0.1818,
        "avgReturn": 0.0454,
        "totalTrades": 11,
        "winRate": 0.8182,
        "maxDrawdown": -0.0462,
        "skippedByEnvironment": 30,
        "skippedByMarket": 12,
        "avgStopLossPct": 0.0413,
        "buyCount": 252,
        "trades": [
          {
            "buyDate": "2022-11-30",
            "sellDate": "2022-12-07",
            "buyPrice": 20,
            "sellPrice": 21.54,
            "return": 0.0757,
            "holdingDays": 5,
            "confidence": 0.6977,
            "stopLossPct": 0.0266,
            "exitReason": "sellSignal"
          },
          {
            "buyDate": "2022-12-09",
            "sellDate": "2022-12-12",
            "buyPrice": 21.65,
            "sellPrice": 22.16,
            "return": 0.0223,
            "holdingDays": 1,
            "confidence": 1,
            "stopLossPct": 0.0417,
            "exitReason": "sellSignal"
          },
          {
            "buyDate": "2024-03-08",
            "sellDate": "2024-03-15",
            "buyPrice": 24.49,
            "sellPrice": 25.79,
            "return": 0.0518,
            "holdingDays": 5,
            "confidence": 0.5378,
            "stopLossPct": 0.0434,
            "exitReason": "sellSignal"
          },
          {
            "buyDate": "2024-07-15",
            "sellDate": "2024-07-23",
            "buyPrice": 21.39,
            "sellPrice": 20.57,
            "return": -0.0396,
            "holdingDays": 6,
            "confidence": 0.612,
            "stopLossPct": 0.0344,
            "exitReason": "stopLoss"
          },
          {
            "buyDate": "2024-09-25",
            "sellDate": "2024-09-26",
            "buyPrice": 19.57,
            "sellPrice": 20.53,
            "return": 0.0478,
            "holdingDays": 1,
            "confidence": 1,
            "stopLossPct": 0.0415,
            "exitReason": "sellSignal"
          },
          {
            "buyDate": "2024-09-30",
            "sellDate": "2024-10-08",
            "buyPrice": 23.14,
            "sellPrice": 23.44,
            "return": 0.0117,
            "holdingDays": 1,
            "confidence": 0.9216,
            "stopLossPct": 0.0491,
            "exitReason": "sellSignal"
          },
          {
            "buyDate": "2024-10-29",
            "sellDate": "2024-12-11",
            "buyPrice": 20.91,
            "sellPrice": 22.35,
            "return": 0.0676,
            "holdingDays": 31,
            "confidence": 0.5252,
            "stopLossPct": 0.0518,
            "exitReason": "sellSignal"
          },
          {
            "buyDate": "2025-04-29",
            "sellDate": "2025-05-06",
            "buyPrice": 24.97,
            "sellPrice": 23.85,
            "return": -0.0462,
            "holdingDays": 2,
            "confidence": 0.8104,
            "stopLossPct": 0.043,
            "exitReason": "stopLoss"
          },
          {
            "buyDate": "2025-07-08",
            "sellDate": "2025-09-02",
            "buyPrice": 21.12,
            "sellPrice": 21.7,
            "return": 0.0262,
            "holdingDays": 40,
            "confidence": 1,
            "stopLossPct": 0.0214,
            "exitReason": "timeout"
          },
          {
            "buyDate": "2025-09-25",
            "sellDate": "2025-09-29",
            "buyPrice": 25.58,
            "sellPrice": 30.3,
            "return": 0.1832,
            "holdingDays": 2,
            "confidence": 1,
            "stopLossPct": 0.041,
            "exitReason": "sellSignal"
          },
          {
            "buyDate": "2025-10-09",
            "sellDate": "2025-10-10",
            "buyPrice": 31.29,
            "sellPrice": 34.42,
            "return": 0.0987,
            "holdingDays": 1,
            "confidence": 1,
            "stopLossPct": 0.06,
            "exitReason": "sellSignal"
          }
        ]
      }
    },
    {
      "rank": 2,
      "config": {
        "minZoneCapture": 0.6,
        "zoneForward": 15,
        "zoneBackward": 3,
        "envFilter": "ma20_or_ma60_rising"
      },
      "bestModel": {
        "featureSet": "volume_price",
        "model": "PercentileRank",
        "precision": 0.3194,
        "recall": 0.7349,
        "f1": 0.4191
      },
      "result": {
        "stopLossRate": 0.1818,
        "avgReturn": 0.0454,
        "totalTrades": 11,
        "winRate": 0.8182,
        "maxDrawdown": -0.0462,
        "skippedByEnvironment": 24,
        "skippedByMarket": 13,
        "avgStopLossPct": 0.0413,
        "buyCount": 264,
        "trades": [
          {
            "buyDate": "2022-11-30",
            "sellDate": "2022-12-07",
            "buyPrice": 20,
            "sellPrice": 21.54,
            "return": 0.0757,
            "holdingDays": 5,
            "confidence": 0.7008,
            "stopLossPct": 0.0266,
            "exitReason": "sellSignal"
          },
          {
            "buyDate": "2022-12-09",
            "sellDate": "2022-12-12",
            "buyPrice": 21.65,
            "sellPrice": 22.16,
            "return": 0.0223,
            "holdingDays": 1,
            "confidence": 1,
            "stopLossPct": 0.0417,
            "exitReason": "sellSignal"
          },
          {
            "buyDate": "2024-03-08",
            "sellDate": "2024-03-15",
            "buyPrice": 24.49,
            "sellPrice": 25.79,
            "return": 0.0518,
            "holdingDays": 5,
            "confidence": 0.5418,
            "stopLossPct": 0.0434,
            "exitReason": "sellSignal"
          },
          {
            "buyDate": "2024-07-15",
            "sellDate": "2024-07-23",
            "buyPrice": 21.39,
            "sellPrice": 20.57,
            "return": -0.0396,
            "holdingDays": 6,
            "confidence": 0.6339,
            "stopLossPct": 0.0344,
            "exitReason": "stopLoss"
          },
          {
            "buyDate": "2024-09-25",
            "sellDate": "2024-09-26",
            "buyPrice": 19.57,
            "sellPrice": 20.53,
            "return": 0.0478,
            "holdingDays": 1,
            "confidence": 1,
            "stopLossPct": 0.0415,
            "exitReason": "sellSignal"
          },
          {
            "buyDate": "2024-09-30",
            "sellDate": "2024-10-08",
            "buyPrice": 23.14,
            "sellPrice": 23.44,
            "return": 0.0117,
            "holdingDays": 1,
            "confidence": 0.9257,
            "stopLossPct": 0.0491,
            "exitReason": "sellSignal"
          },
          {
            "buyDate": "2024-10-29",
            "sellDate": "2024-12-11",
            "buyPrice": 20.91,
            "sellPrice": 22.35,
            "return": 0.0676,
            "holdingDays": 31,
            "confidence": 0.5293,
            "stopLossPct": 0.0518,
            "exitReason": "sellSignal"
          },
          {
            "buyDate": "2025-04-29",
            "sellDate": "2025-05-06",
            "buyPrice": 24.97,
            "sellPrice": 23.85,
            "return": -0.0462,
            "holdingDays": 2,
            "confidence": 0.9481,
            "stopLossPct": 0.043,
            "exitReason": "stopLoss"
          },
          {
            "buyDate": "2025-07-08",
            "sellDate": "2025-09-02",
            "buyPrice": 21.12,
            "sellPrice": 21.7,
            "return": 0.0262,
            "holdingDays": 40,
            "confidence": 1,
            "stopLossPct": 0.0214,
            "exitReason": "timeout"
          },
          {
            "buyDate": "2025-09-25",
            "sellDate": "2025-09-29",
            "buyPrice": 25.58,
            "sellPrice": 30.3,
            "return": 0.1832,
            "holdingDays": 2,
            "confidence": 1,
            "stopLossPct": 0.041,
            "exitReason": "sellSignal"
          },
          {
            "buyDate": "2025-10-09",
            "sellDate": "2025-10-10",
            "buyPrice": 31.29,
            "sellPrice": 34.42,
            "return": 0.0987,
            "holdingDays": 1,
            "confidence": 1,
            "stopLossPct": 0.06,
            "exitReason": "sellSignal"
          }
        ]
      }
    },
    {
      "rank": 3,
      "config": {
        "minZoneCapture": 0.7,
        "zoneForward": 15,
        "zoneBackward": 5,
        "envFilter": "ma20_or_ma60_rising"
      },
      "bestModel": {
        "featureSet": "volume_price",
        "model": "PercentileRank",
        "precision": 0.3225,
        "recall": 0.7524,
        "f1": 0.4276
      },
      "result": {
        "stopLossRate": 0.1818,
        "avgReturn": 0.0454,
        "totalTrades": 11,
        "winRate": 0.8182,
        "maxDrawdown": -0.0462,
        "skippedByEnvironment": 30,
        "skippedByMarket": 10,
        "avgStopLossPct": 0.0413,
        "buyCount": 263,
        "trades": [
          {
            "buyDate": "2022-11-30",
            "sellDate": "2022-12-07",
            "buyPrice": 20,
            "sellPrice": 21.54,
            "return": 0.0757,
            "holdingDays": 5,
            "confidence": 0.5453,
            "stopLossPct": 0.0266,
            "exitReason": "sellSignal"
          },
          {
            "buyDate": "2022-12-09",
            "sellDate": "2022-12-12",
            "buyPrice": 21.65,
            "sellPrice": 22.16,
            "return": 0.0223,
            "holdingDays": 1,
            "confidence": 1,
            "stopLossPct": 0.0417,
            "exitReason": "sellSignal"
          },
          {
            "buyDate": "2024-03-08",
            "sellDate": "2024-03-15",
            "buyPrice": 24.49,
            "sellPrice": 25.79,
            "return": 0.0518,
            "holdingDays": 5,
            "confidence": 0.5486,
            "stopLossPct": 0.0434,
            "exitReason": "sellSignal"
          },
          {
            "buyDate": "2024-07-15",
            "sellDate": "2024-07-23",
            "buyPrice": 21.39,
            "sellPrice": 20.57,
            "return": -0.0396,
            "holdingDays": 6,
            "confidence": 0.5884,
            "stopLossPct": 0.0344,
            "exitReason": "stopLoss"
          },
          {
            "buyDate": "2024-09-25",
            "sellDate": "2024-09-26",
            "buyPrice": 19.57,
            "sellPrice": 20.53,
            "return": 0.0478,
            "holdingDays": 1,
            "confidence": 0.9999,
            "stopLossPct": 0.0415,
            "exitReason": "sellSignal"
          },
          {
            "buyDate": "2024-09-30",
            "sellDate": "2024-10-08",
            "buyPrice": 23.14,
            "sellPrice": 23.44,
            "return": 0.0117,
            "holdingDays": 1,
            "confidence": 0.9149,
            "stopLossPct": 0.0491,
            "exitReason": "sellSignal"
          },
          {
            "buyDate": "2024-10-29",
            "sellDate": "2024-12-11",
            "buyPrice": 20.91,
            "sellPrice": 22.35,
            "return": 0.0676,
            "holdingDays": 31,
            "confidence": 0.5185,
            "stopLossPct": 0.0518,
            "exitReason": "sellSignal"
          },
          {
            "buyDate": "2025-04-29",
            "sellDate": "2025-05-06",
            "buyPrice": 24.97,
            "sellPrice": 23.85,
            "return": -0.0462,
            "holdingDays": 2,
            "confidence": 0.9623,
            "stopLossPct": 0.043,
            "exitReason": "stopLoss"
          },
          {
            "buyDate": "2025-07-08",
            "sellDate": "2025-09-02",
            "buyPrice": 21.12,
            "sellPrice": 21.7,
            "return": 0.0262,
            "holdingDays": 40,
            "confidence": 1,
            "stopLossPct": 0.0214,
            "exitReason": "timeout"
          },
          {
            "buyDate": "2025-09-25",
            "sellDate": "2025-09-29",
            "buyPrice": 25.58,
            "sellPrice": 30.3,
            "return": 0.1832,
            "holdingDays": 2,
            "confidence": 1,
            "stopLossPct": 0.041,
            "exitReason": "sellSignal"
          },
          {
            "buyDate": "2025-10-09",
            "sellDate": "2025-10-10",
            "buyPrice": 31.29,
            "sellPrice": 34.42,
            "return": 0.0987,
            "holdingDays": 1,
            "confidence": 1,
            "stopLossPct": 0.06,
            "exitReason": "sellSignal"
          }
        ]
      }
    },
    {
      "rank": 4,
      "config": {
        "minZoneCapture": 0.5,
        "zoneForward": 15,
        "zoneBackward": 3,
        "envFilter": "ma20_or_ma60_rising"
      },
      "bestModel": {
        "featureSet": "volume_price",
        "model": "PercentileRank",
        "precision": 0.3485,
        "recall": 0.7117,
        "f1": 0.4339
      },
      "result": {
        "stopLossRate": 0.1818,
        "avgReturn": 0.0446,
        "totalTrades": 11,
        "winRate": 0.8182,
        "maxDrawdown": -0.0485,
        "skippedByEnvironment": 27,
        "skippedByMarket": 13,
        "avgStopLossPct": 0.0409,
        "buyCount": 288,
        "trades": [
          {
            "buyDate": "2022-11-30",
            "sellDate": "2022-12-07",
            "buyPrice": 20,
            "sellPrice": 21.54,
            "return": 0.0757,
            "holdingDays": 5,
            "confidence": 0.8473,
            "stopLossPct": 0.0266,
            "exitReason": "sellSignal"
          },
          {
            "buyDate": "2022-12-09",
            "sellDate": "2022-12-12",
            "buyPrice": 21.65,
            "sellPrice": 22.16,
            "return": 0.0223,
            "holdingDays": 1,
            "confidence": 1,
            "stopLossPct": 0.0417,
            "exitReason": "sellSignal"
          },
          {
            "buyDate": "2024-03-08",
            "sellDate": "2024-03-15",
            "buyPrice": 24.49,
            "sellPrice": 25.79,
            "return": 0.0518,
            "holdingDays": 5,
            "confidence": 0.5774,
            "stopLossPct": 0.0434,
            "exitReason": "sellSignal"
          },
          {
            "buyDate": "2024-07-19",
            "sellDate": "2024-07-23",
            "buyPrice": 21.59,
            "sellPrice": 20.57,
            "return": -0.0485,
            "holdingDays": 2,
            "confidence": 0.6002,
            "stopLossPct": 0.0303,
            "exitReason": "stopLoss"
          },
          {
            "buyDate": "2024-09-25",
            "sellDate": "2024-09-26",
            "buyPrice": 19.57,
            "sellPrice": 20.53,
            "return": 0.0478,
            "holdingDays": 1,
            "confidence": 1,
            "stopLossPct": 0.0415,
            "exitReason": "sellSignal"
          },
          {
            "buyDate": "2024-09-30",
            "sellDate": "2024-10-08",
            "buyPrice": 23.14,
            "sellPrice": 23.44,
            "return": 0.0117,
            "holdingDays": 1,
            "confidence": 1,
            "stopLossPct": 0.0491,
            "exitReason": "sellSignal"
          },
          {
            "buyDate": "2024-10-29",
            "sellDate": "2024-12-11",
            "buyPrice": 20.91,
            "sellPrice": 22.35,
            "return": 0.0676,
            "holdingDays": 31,
            "confidence": 0.6881,
            "stopLossPct": 0.0518,
            "exitReason": "sellSignal"
          },
          {
            "buyDate": "2025-04-29",
            "sellDate": "2025-05-06",
            "buyPrice": 24.97,
            "sellPrice": 23.85,
            "return": -0.0462,
            "holdingDays": 2,
            "confidence": 1,
            "stopLossPct": 0.043,
            "exitReason": "stopLoss"
          },
          {
            "buyDate": "2025-07-08",
            "sellDate": "2025-09-02",
            "buyPrice": 21.12,
            "sellPrice": 21.7,
            "return": 0.0262,
            "holdingDays": 40,
            "confidence": 1,
            "stopLossPct": 0.0214,
            "exitReason": "timeout"
          },
          {
            "buyDate": "2025-09-25",
            "sellDate": "2025-09-29",
            "buyPrice": 25.58,
            "sellPrice": 30.3,
            "return": 0.1832,
            "holdingDays": 2,
            "confidence": 1,
            "stopLossPct": 0.041,
            "exitReason": "sellSignal"
          },
          {
            "buyDate": "2025-10-09",
            "sellDate": "2025-10-10",
            "buyPrice": 31.29,
            "sellPrice": 34.42,
            "return": 0.0987,
            "holdingDays": 1,
            "confidence": 1,
            "stopLossPct": 0.06,
            "exitReason": "sellSignal"
          }
        ]
      }
    },
    {
      "rank": 5,
      "config": {
        "minZoneCapture": 0.6,
        "zoneForward": 15,
        "zoneBackward": 2,
        "envFilter": "ma20_0.98"
      },
      "bestModel": {
        "featureSet": "volume_price",
        "model": "PercentileRank",
        "precision": 0.3078,
        "recall": 0.7094,
        "f1": 0.4045
      },
      "result": {
        "stopLossRate": 0.2,
        "avgReturn": 0.0432,
        "totalTrades": 10,
        "winRate": 0.8,
        "maxDrawdown": -0.0462,
        "skippedByEnvironment": 31,
        "skippedByMarket": 12,
        "avgStopLossPct": 0.0402,
        "buyCount": 252,
        "trades": [
          {
            "buyDate": "2022-11-30",
            "sellDate": "2022-12-07",
            "buyPrice": 20,
            "sellPrice": 21.54,
            "return": 0.0757,
            "holdingDays": 5,
            "confidence": 0.6977,
            "stopLossPct": 0.0266,
            "exitReason": "sellSignal"
          },
          {
            "buyDate": "2022-12-09",
            "sellDate": "2022-12-12",
            "buyPrice": 21.65,
            "sellPrice": 22.16,
            "return": 0.0223,
            "holdingDays": 1,
            "confidence": 1,
            "stopLossPct": 0.0417,
            "exitReason": "sellSignal"
          },
          {
            "buyDate": "2024-03-08",
            "sellDate": "2024-03-15",
            "buyPrice": 24.49,
            "sellPrice": 25.79,
            "return": 0.0518,
            "holdingDays": 5,
            "confidence": 0.5378,
            "stopLossPct": 0.0434,
            "exitReason": "sellSignal"
          },
          {
            "buyDate": "2024-07-15",
            "sellDate": "2024-07-23",
            "buyPrice": 21.39,
            "sellPrice": 20.57,
            "return": -0.0396,
            "holdingDays": 6,
            "confidence": 0.612,
            "stopLossPct": 0.0344,
            "exitReason": "stopLoss"
          },
          {
            "buyDate": "2024-09-25",
            "sellDate": "2024-09-26",
            "buyPrice": 19.57,
            "sellPrice": 20.53,
            "return": 0.0478,
            "holdingDays": 1,
            "confidence": 1,
            "stopLossPct": 0.0415,
            "exitReason": "sellSignal"
          },
          {
            "buyDate": "2024-09-30",
            "sellDate": "2024-10-08",
            "buyPrice": 23.14,
            "sellPrice": 23.44,
            "return": 0.0117,
            "holdingDays": 1,
            "confidence": 0.9216,
            "stopLossPct": 0.0491,
            "exitReason": "sellSignal"
          },
          {
            "buyDate": "2025-04-29",
            "sellDate": "2025-05-06",
            "buyPrice": 24.97,
            "sellPrice": 23.85,
            "return": -0.0462,
            "holdingDays": 2,
            "confidence": 0.8104,
            "stopLossPct": 0.043,
            "exitReason": "stopLoss"
          },
          {
            "buyDate": "2025-07-08",
            "sellDate": "2025-09-02",
            "buyPrice": 21.12,
            "sellPrice": 21.7,
            "return": 0.0262,
            "holdingDays": 40,
            "confidence": 1,
            "stopLossPct": 0.0214,
            "exitReason": "timeout"
          },
          {
            "buyDate": "2025-09-25",
            "sellDate": "2025-09-29",
            "buyPrice": 25.58,
            "sellPrice": 30.3,
            "return": 0.1832,
            "holdingDays": 2,
            "confidence": 1,
            "stopLossPct": 0.041,
            "exitReason": "sellSignal"
          },
          {
            "buyDate": "2025-10-09",
            "sellDate": "2025-10-10",
            "buyPrice": 31.29,
            "sellPrice": 34.42,
            "return": 0.0987,
            "holdingDays": 1,
            "confidence": 1,
            "stopLossPct": 0.06,
            "exitReason": "sellSignal"
          }
        ]
      }
    },
    {
      "rank": 6,
      "config": {
        "minZoneCapture": 0.6,
        "zoneForward": 15,
        "zoneBackward": 3,
        "envFilter": "ma20_0.98"
      },
      "bestModel": {
        "featureSet": "volume_price",
        "model": "PercentileRank",
        "precision": 0.3194,
        "recall": 0.7349,
        "f1": 0.4191
      },
      "result": {
        "stopLossRate": 0.2,
        "avgReturn": 0.0432,
        "totalTrades": 10,
        "winRate": 0.8,
        "maxDrawdown": -0.0462,
        "skippedByEnvironment": 25,
        "skippedByMarket": 13,
        "avgStopLossPct": 0.0402,
        "buyCount": 264,
        "trades": [
          {
            "buyDate": "2022-11-30",
            "sellDate": "2022-12-07",
            "buyPrice": 20,
            "sellPrice": 21.54,
            "return": 0.0757,
            "holdingDays": 5,
            "confidence": 0.7008,
            "stopLossPct": 0.0266,
            "exitReason": "sellSignal"
          },
          {
            "buyDate": "2022-12-09",
            "sellDate": "2022-12-12",
            "buyPrice": 21.65,
            "sellPrice": 22.16,
            "return": 0.0223,
            "holdingDays": 1,
            "confidence": 1,
            "stopLossPct": 0.0417,
            "exitReason": "sellSignal"
          },
          {
            "buyDate": "2024-03-08",
            "sellDate": "2024-03-15",
            "buyPrice": 24.49,
            "sellPrice": 25.79,
            "return": 0.0518,
            "holdingDays": 5,
            "confidence": 0.5418,
            "stopLossPct": 0.0434,
            "exitReason": "sellSignal"
          },
          {
            "buyDate": "2024-07-15",
            "sellDate": "2024-07-23",
            "buyPrice": 21.39,
            "sellPrice": 20.57,
            "return": -0.0396,
            "holdingDays": 6,
            "confidence": 0.6339,
            "stopLossPct": 0.0344,
            "exitReason": "stopLoss"
          },
          {
            "buyDate": "2024-09-25",
            "sellDate": "2024-09-26",
            "buyPrice": 19.57,
            "sellPrice": 20.53,
            "return": 0.0478,
            "holdingDays": 1,
            "confidence": 1,
            "stopLossPct": 0.0415,
            "exitReason": "sellSignal"
          },
          {
            "buyDate": "2024-09-30",
            "sellDate": "2024-10-08",
            "buyPrice": 23.14,
            "sellPrice": 23.44,
            "return": 0.0117,
            "holdingDays": 1,
            "confidence": 0.9257,
            "stopLossPct": 0.0491,
            "exitReason": "sellSignal"
          },
          {
            "buyDate": "2025-04-29",
            "sellDate": "2025-05-06",
            "buyPrice": 24.97,
            "sellPrice": 23.85,
            "return": -0.0462,
            "holdingDays": 2,
            "confidence": 0.9481,
            "stopLossPct": 0.043,
            "exitReason": "stopLoss"
          },
          {
            "buyDate": "2025-07-08",
            "sellDate": "2025-09-02",
            "buyPrice": 21.12,
            "sellPrice": 21.7,
            "return": 0.0262,
            "holdingDays": 40,
            "confidence": 1,
            "stopLossPct": 0.0214,
            "exitReason": "timeout"
          },
          {
            "buyDate": "2025-09-25",
            "sellDate": "2025-09-29",
            "buyPrice": 25.58,
            "sellPrice": 30.3,
            "return": 0.1832,
            "holdingDays": 2,
            "confidence": 1,
            "stopLossPct": 0.041,
            "exitReason": "sellSignal"
          },
          {
            "buyDate": "2025-10-09",
            "sellDate": "2025-10-10",
            "buyPrice": 31.29,
            "sellPrice": 34.42,
            "return": 0.0987,
            "holdingDays": 1,
            "confidence": 1,
            "stopLossPct": 0.06,
            "exitReason": "sellSignal"
          }
        ]
      }
    },
    {
      "rank": 7,
      "config": {
        "minZoneCapture": 0.7,
        "zoneForward": 15,
        "zoneBackward": 5,
        "envFilter": "ma20_0.98"
      },
      "bestModel": {
        "featureSet": "volume_price",
        "model": "PercentileRank",
        "precision": 0.3225,
        "recall": 0.7524,
        "f1": 0.4276
      },
      "result": {
        "stopLossRate": 0.2,
        "avgReturn": 0.0432,
        "totalTrades": 10,
        "winRate": 0.8,
        "maxDrawdown": -0.0462,
        "skippedByEnvironment": 31,
        "skippedByMarket": 10,
        "avgStopLossPct": 0.0402,
        "buyCount": 263,
        "trades": [
          {
            "buyDate": "2022-11-30",
            "sellDate": "2022-12-07",
            "buyPrice": 20,
            "sellPrice": 21.54,
            "return": 0.0757,
            "holdingDays": 5,
            "confidence": 0.5453,
            "stopLossPct": 0.0266,
            "exitReason": "sellSignal"
          },
          {
            "buyDate": "2022-12-09",
            "sellDate": "2022-12-12",
            "buyPrice": 21.65,
            "sellPrice": 22.16,
            "return": 0.0223,
            "holdingDays": 1,
            "confidence": 1,
            "stopLossPct": 0.0417,
            "exitReason": "sellSignal"
          },
          {
            "buyDate": "2024-03-08",
            "sellDate": "2024-03-15",
            "buyPrice": 24.49,
            "sellPrice": 25.79,
            "return": 0.0518,
            "holdingDays": 5,
            "confidence": 0.5486,
            "stopLossPct": 0.0434,
            "exitReason": "sellSignal"
          },
          {
            "buyDate": "2024-07-15",
            "sellDate": "2024-07-23",
            "buyPrice": 21.39,
            "sellPrice": 20.57,
            "return": -0.0396,
            "holdingDays": 6,
            "confidence": 0.5884,
            "stopLossPct": 0.0344,
            "exitReason": "stopLoss"
          },
          {
            "buyDate": "2024-09-25",
            "sellDate": "2024-09-26",
            "buyPrice": 19.57,
            "sellPrice": 20.53,
            "return": 0.0478,
            "holdingDays": 1,
            "confidence": 0.9999,
            "stopLossPct": 0.0415,
            "exitReason": "sellSignal"
          },
          {
            "buyDate": "2024-09-30",
            "sellDate": "2024-10-08",
            "buyPrice": 23.14,
            "sellPrice": 23.44,
            "return": 0.0117,
            "holdingDays": 1,
            "confidence": 0.9149,
            "stopLossPct": 0.0491,
            "exitReason": "sellSignal"
          },
          {
            "buyDate": "2025-04-29",
            "sellDate": "2025-05-06",
            "buyPrice": 24.97,
            "sellPrice": 23.85,
            "return": -0.0462,
            "holdingDays": 2,
            "confidence": 0.9623,
            "stopLossPct": 0.043,
            "exitReason": "stopLoss"
          },
          {
            "buyDate": "2025-07-08",
            "sellDate": "2025-09-02",
            "buyPrice": 21.12,
            "sellPrice": 21.7,
            "return": 0.0262,
            "holdingDays": 40,
            "confidence": 1,
            "stopLossPct": 0.0214,
            "exitReason": "timeout"
          },
          {
            "buyDate": "2025-09-25",
            "sellDate": "2025-09-29",
            "buyPrice": 25.58,
            "sellPrice": 30.3,
            "return": 0.1832,
            "holdingDays": 2,
            "confidence": 1,
            "stopLossPct": 0.041,
            "exitReason": "sellSignal"
          },
          {
            "buyDate": "2025-10-09",
            "sellDate": "2025-10-10",
            "buyPrice": 31.29,
            "sellPrice": 34.42,
            "return": 0.0987,
            "holdingDays": 1,
            "confidence": 1,
            "stopLossPct": 0.06,
            "exitReason": "sellSignal"
          }
        ]
      }
    },
    {
      "rank": 8,
      "config": {
        "minZoneCapture": 0.5,
        "zoneForward": 15,
        "zoneBackward": 3,
        "envFilter": "ma20_0.98"
      },
      "bestModel": {
        "featureSet": "volume_price",
        "model": "PercentileRank",
        "precision": 0.3485,
        "recall": 0.7117,
        "f1": 0.4339
      },
      "result": {
        "stopLossRate": 0.2,
        "avgReturn": 0.0423,
        "totalTrades": 10,
        "winRate": 0.8,
        "maxDrawdown": -0.0485,
        "skippedByEnvironment": 28,
        "skippedByMarket": 13,
        "avgStopLossPct": 0.0398,
        "buyCount": 288,
        "trades": [
          {
            "buyDate": "2022-11-30",
            "sellDate": "2022-12-07",
            "buyPrice": 20,
            "sellPrice": 21.54,
            "return": 0.0757,
            "holdingDays": 5,
            "confidence": 0.8473,
            "stopLossPct": 0.0266,
            "exitReason": "sellSignal"
          },
          {
            "buyDate": "2022-12-09",
            "sellDate": "2022-12-12",
            "buyPrice": 21.65,
            "sellPrice": 22.16,
            "return": 0.0223,
            "holdingDays": 1,
            "confidence": 1,
            "stopLossPct": 0.0417,
            "exitReason": "sellSignal"
          },
          {
            "buyDate": "2024-03-08",
            "sellDate": "2024-03-15",
            "buyPrice": 24.49,
            "sellPrice": 25.79,
            "return": 0.0518,
            "holdingDays": 5,
            "confidence": 0.5774,
            "stopLossPct": 0.0434,
            "exitReason": "sellSignal"
          },
          {
            "buyDate": "2024-07-19",
            "sellDate": "2024-07-23",
            "buyPrice": 21.59,
            "sellPrice": 20.57,
            "return": -0.0485,
            "holdingDays": 2,
            "confidence": 0.6002,
            "stopLossPct": 0.0303,
            "exitReason": "stopLoss"
          },
          {
            "buyDate": "2024-09-25",
            "sellDate": "2024-09-26",
            "buyPrice": 19.57,
            "sellPrice": 20.53,
            "return": 0.0478,
            "holdingDays": 1,
            "confidence": 1,
            "stopLossPct": 0.0415,
            "exitReason": "sellSignal"
          },
          {
            "buyDate": "2024-09-30",
            "sellDate": "2024-10-08",
            "buyPrice": 23.14,
            "sellPrice": 23.44,
            "return": 0.0117,
            "holdingDays": 1,
            "confidence": 1,
            "stopLossPct": 0.0491,
            "exitReason": "sellSignal"
          },
          {
            "buyDate": "2025-04-29",
            "sellDate": "2025-05-06",
            "buyPrice": 24.97,
            "sellPrice": 23.85,
            "return": -0.0462,
            "holdingDays": 2,
            "confidence": 1,
            "stopLossPct": 0.043,
            "exitReason": "stopLoss"
          },
          {
            "buyDate": "2025-07-08",
            "sellDate": "2025-09-02",
            "buyPrice": 21.12,
            "sellPrice": 21.7,
            "return": 0.0262,
            "holdingDays": 40,
            "confidence": 1,
            "stopLossPct": 0.0214,
            "exitReason": "timeout"
          },
          {
            "buyDate": "2025-09-25",
            "sellDate": "2025-09-29",
            "buyPrice": 25.58,
            "sellPrice": 30.3,
            "return": 0.1832,
            "holdingDays": 2,
            "confidence": 1,
            "stopLossPct": 0.041,
            "exitReason": "sellSignal"
          },
          {
            "buyDate": "2025-10-09",
            "sellDate": "2025-10-10",
            "buyPrice": 31.29,
            "sellPrice": 34.42,
            "return": 0.0987,
            "holdingDays": 1,
            "confidence": 1,
            "stopLossPct": 0.06,
            "exitReason": "sellSignal"
          }
        ]
      }
    },
    {
      "rank": 9,
      "config": {
        "minZoneCapture": 0.5,
        "zoneForward": 15,
        "zoneBackward": 2,
        "envFilter": "ma20_or_ma60_rising"
      },
      "bestModel": {
        "featureSet": "volume_price",
        "model": "PercentileRank",
        "precision": 0.3294,
        "recall": 0.6793,
        "f1": 0.4116
      },
      "result": {
        "stopLossRate": 0.1667,
        "avgReturn": 0.0403,
        "totalTrades": 12,
        "winRate": 0.75,
        "maxDrawdown": -0.0485,
        "skippedByEnvironment": 26,
        "skippedByMarket": 14,
        "avgStopLossPct": 0.0425,
        "buyCount": 274,
        "trades": [
          {
            "buyDate": "2022-11-30",
            "sellDate": "2022-12-07",
            "buyPrice": 20,
            "sellPrice": 21.54,
            "return": 0.0757,
            "holdingDays": 5,
            "confidence": 0.6423,
            "stopLossPct": 0.0266,
            "exitReason": "sellSignal"
          },
          {
            "buyDate": "2022-12-09",
            "sellDate": "2022-12-12",
            "buyPrice": 21.65,
            "sellPrice": 22.16,
            "return": 0.0223,
            "holdingDays": 1,
            "confidence": 1,
            "stopLossPct": 0.0417,
            "exitReason": "sellSignal"
          },
          {
            "buyDate": "2024-03-08",
            "sellDate": "2024-03-15",
            "buyPrice": 24.49,
            "sellPrice": 25.79,
            "return": 0.0518,
            "holdingDays": 5,
            "confidence": 0.5716,
            "stopLossPct": 0.0434,
            "exitReason": "sellSignal"
          },
          {
            "buyDate": "2024-07-19",
            "sellDate": "2024-07-23",
            "buyPrice": 21.59,
            "sellPrice": 20.57,
            "return": -0.0485,
            "holdingDays": 2,
            "confidence": 0.576,
            "stopLossPct": 0.0303,
            "exitReason": "stopLoss"
          },
          {
            "buyDate": "2024-09-25",
            "sellDate": "2024-09-26",
            "buyPrice": 19.57,
            "sellPrice": 20.53,
            "return": 0.0478,
            "holdingDays": 1,
            "confidence": 0.645,
            "stopLossPct": 0.0415,
            "exitReason": "sellSignal"
          },
          {
            "buyDate": "2024-09-30",
            "sellDate": "2024-10-08",
            "buyPrice": 23.14,
            "sellPrice": 23.44,
            "return": 0.0117,
            "holdingDays": 1,
            "confidence": 0.714,
            "stopLossPct": 0.0491,
            "exitReason": "sellSignal"
          },
          {
            "buyDate": "2024-10-10",
            "sellDate": "2024-10-11",
            "buyPrice": 21.98,
            "sellPrice": 21.86,
            "return": -0.0068,
            "holdingDays": 1,
            "confidence": 0.7446,
            "stopLossPct": 0.06,
            "exitReason": "sellSignal"
          },
          {
            "buyDate": "2024-10-29",
            "sellDate": "2024-12-11",
            "buyPrice": 20.91,
            "sellPrice": 22.35,
            "return": 0.0676,
            "holdingDays": 31,
            "confidence": 0.6321,
            "stopLossPct": 0.0518,
            "exitReason": "sellSignal"
          },
          {
            "buyDate": "2025-04-29",
            "sellDate": "2025-05-06",
            "buyPrice": 24.97,
            "sellPrice": 23.85,
            "return": -0.0462,
            "holdingDays": 2,
            "confidence": 0.9481,
            "stopLossPct": 0.043,
            "exitReason": "stopLoss"
          },
          {
            "buyDate": "2025-07-08",
            "sellDate": "2025-09-02",
            "buyPrice": 21.12,
            "sellPrice": 21.7,
            "return": 0.0262,
            "holdingDays": 40,
            "confidence": 1,
            "stopLossPct": 0.0214,
            "exitReason": "timeout"
          },
          {
            "buyDate": "2025-09-25",
            "sellDate": "2025-09-29",
            "buyPrice": 25.58,
            "sellPrice": 30.3,
            "return": 0.1832,
            "holdingDays": 2,
            "confidence": 1,
            "stopLossPct": 0.041,
            "exitReason": "sellSignal"
          },
          {
            "buyDate": "2025-10-09",
            "sellDate": "2025-10-10",
            "buyPrice": 31.29,
            "sellPrice": 34.42,
            "return": 0.0987,
            "holdingDays": 1,
            "confidence": 1,
            "stopLossPct": 0.06,
            "exitReason": "sellSignal"
          }
        ]
      }
    },
    {
      "rank": 10,
      "config": {
        "minZoneCapture": 0.5,
        "zoneForward": 15,
        "zoneBackward": 2,
        "envFilter": "ma20"
      },
      "bestModel": {
        "featureSet": "volume_price",
        "model": "PercentileRank",
        "precision": 0.3294,
        "recall": 0.6793,
        "f1": 0.4116
      },
      "result": {
        "stopLossRate": 0.2,
        "avgReturn": 0.0382,
        "totalTrades": 10,
        "winRate": 0.7,
        "maxDrawdown": -0.0527,
        "skippedByEnvironment": 35,
        "skippedByMarket": 10,
        "avgStopLossPct": 0.0413,
        "buyCount": 274,
        "trades": [
          {
            "buyDate": "2022-11-30",
            "sellDate": "2022-12-07",
            "buyPrice": 20,
            "sellPrice": 21.54,
            "return": 0.0757,
            "holdingDays": 5,
            "confidence": 0.6423,
            "stopLossPct": 0.0266,
            "exitReason": "sellSignal"
          },
          {
            "buyDate": "2022-12-09",
            "sellDate": "2022-12-12",
            "buyPrice": 21.65,
            "sellPrice": 22.16,
            "return": 0.0223,
            "holdingDays": 1,
            "confidence": 1,
            "stopLossPct": 0.0417,
            "exitReason": "sellSignal"
          },
          {
            "buyDate": "2024-07-19",
            "sellDate": "2024-07-23",
            "buyPrice": 21.59,
            "sellPrice": 20.57,
            "return": -0.0485,
            "holdingDays": 2,
            "confidence": 0.576,
            "stopLossPct": 0.0303,
            "exitReason": "stopLoss"
          },
          {
            "buyDate": "2024-09-25",
            "sellDate": "2024-09-26",
            "buyPrice": 19.57,
            "sellPrice": 20.53,
            "return": 0.0478,
            "holdingDays": 1,
            "confidence": 0.645,
            "stopLossPct": 0.0415,
            "exitReason": "sellSignal"
          },
          {
            "buyDate": "2024-09-30",
            "sellDate": "2024-10-08",
            "buyPrice": 23.14,
            "sellPrice": 23.44,
            "return": 0.0117,
            "holdingDays": 1,
            "confidence": 0.714,
            "stopLossPct": 0.0491,
            "exitReason": "sellSignal"
          },
          {
            "buyDate": "2024-10-10",
            "sellDate": "2024-10-11",
            "buyPrice": 21.98,
            "sellPrice": 21.86,
            "return": -0.0068,
            "holdingDays": 1,
            "confidence": 0.7446,
            "stopLossPct": 0.06,
            "exitReason": "sellSignal"
          },
          {
            "buyDate": "2025-04-29",
            "sellDate": "2025-05-06",
            "buyPrice": 24.97,
            "sellPrice": 23.85,
            "return": -0.0462,
            "holdingDays": 2,
            "confidence": 0.9481,
            "stopLossPct": 0.043,
            "exitReason": "stopLoss"
          },
          {
            "buyDate": "2025-07-14",
            "sellDate": "2025-09-08",
            "buyPrice": 21.34,
            "sellPrice": 22.3,
            "return": 0.0437,
            "holdingDays": 40,
            "confidence": 0.6588,
            "stopLossPct": 0.02,
            "exitReason": "timeout"
          },
          {
            "buyDate": "2025-09-25",
            "sellDate": "2025-09-29",
            "buyPrice": 25.58,
            "sellPrice": 30.3,
            "return": 0.1832,
            "holdingDays": 2,
            "confidence": 1,
            "stopLossPct": 0.041,
            "exitReason": "sellSignal"
          },
          {
            "buyDate": "2025-10-09",
            "sellDate": "2025-10-10",
            "buyPrice": 31.29,
            "sellPrice": 34.42,
            "return": 0.0987,
            "holdingDays": 1,
            "confidence": 1,
            "stopLossPct": 0.06,
            "exitReason": "sellSignal"
          }
        ]
      }
    }
  ],
  "stats": {
    "totalCombinations": 180,
    "validCombinations": 65,
    "scanDurationMs": 41038
  }
}